seamm_dashboard/__init__.py
seamm_dashboard/_version.py
seamm_dashboard/config.py
seamm_dashboard/flask_authorize_patch.py
seamm_dashboard/jwt_patch.py
seamm_dashboard/results_dashboard.py
seamm_dashboard/setup_argparsing.py
seamm_dashboard/setup_logging.py
seamm_dashboard/swagger.yml
seamm_dashboard/template_filters.py
seamm_dashboard/util.py
seamm_dashboard/routes/admin/__init__.py
seamm_dashboard/routes/admin/forms.py
seamm_dashboard/routes/admin/views.py
seamm_dashboard/routes/api/__init__.py
seamm_dashboard/routes/api/auth.py
seamm_dashboard/routes/api/flowcharts.py
seamm_dashboard/routes/api/groups.py
seamm_dashboard/routes/api/jobs.py
seamm_dashboard/routes/api/projects.py
seamm_dashboard/routes/api/roles.py
seamm_dashboard/routes/api/status.py
seamm_dashboard/routes/api/users.py
seamm_dashboard/routes/auth/__init__.py
seamm_dashboard/routes/auth/forms.py
seamm_dashboard/routes/auth/views.py
seamm_dashboard/routes/flowcharts/__init__.py
seamm_dashboard/routes/flowcharts/views.py
seamm_dashboard/routes/jobs/__init__.py
seamm_dashboard/routes/jobs/forms.py
seamm_dashboard/routes/jobs/views.py
seamm_dashboard/routes/main/__init__.py
seamm_dashboard/routes/main/errors.py
seamm_dashboard/routes/main/forms.py
seamm_dashboard/routes/main/views.py
seamm_dashboard/routes/projects/__init__.py
seamm_dashboard/routes/projects/forms.py
seamm_dashboard/routes/projects/views.py
seamm_dashboard/static/.gitignore
seamm_dashboard/static/only_needed_files.py
seamm_dashboard/static/package-lock.json
seamm_dashboard/static/package.json
seamm_dashboard/static/css/bootstrap-select.min.css
seamm_dashboard/static/css/custom.css
seamm_dashboard/static/css/custom_flowchart.css
seamm_dashboard/static/css/jobs_list.css
seamm_dashboard/static/css/prism.css
seamm_dashboard/static/css/style.css
seamm_dashboard/static/css/style.css.map
seamm_dashboard/static/css/style.min.css
seamm_dashboard/static/css/style.min.css.map
seamm_dashboard/static/images/Banner_AllCaps.jpg
seamm_dashboard-2024.6.2.dist-info/LICENSE
seamm_dashboard-2024.6.2.dist-info/METADATA
seamm_dashboard-2024.6.2.dist-info/WHEEL
seamm_dashboard-2024.6.2.dist-info/entry_points.txt
seamm_dashboard-2024.6.2.dist-info/top_level.txt
seamm_dashboard-2024.6.2.dist-info/RECORD
