Metadata-Version: 2.1
Name: seamm-dashboard
Version: 2024.6.2
Summary: The Web Dashboard for SEAMM (Simulation Environment for Atomistic and Molecular Simulations).
Home-page: https://github.com/molssi-seamm/seamm_dashboard.git
Author: Jessica Nash
Author-email: janash@vt.edu
License: BSD-3C
Classifier: Development Status :: 4 - Beta
Classifier: Intended Audience :: Science/Research
Classifier: License :: OSI Approved :: BSD License
Classifier: Natural Language :: English
Classifier: Programming Language :: Python :: 3 :: Only
Classifier: Programming Language :: Python :: 3.8
License-File: LICENSE
Requires-Dist: connexion
Requires-Dist: email-validator
Requires-Dist: fasteners
Requires-Dist: flask
Requires-Dist: flask-authorize
Requires-Dist: flask-bootstrap
Requires-Dist: flask-cors
Requires-Dist: flask-jwt-extended >=4.1.0
Requires-Dist: flask-mail
Requires-Dist: flask-marshmallow
Requires-Dist: flask-moment
Requires-Dist: flask-sqlalchemy
Requires-Dist: flask-wtf
Requires-Dist: seamm-datastore
Requires-Dist: seamm-util
Requires-Dist: six
Requires-Dist: sqlalchemy <2.0
Requires-Dist: swagger-ui-bundle
Requires-Dist: wtforms
Requires-Dist: flask-compress
Requires-Dist: waitress
Provides-Extra: tests
